trollimage-1.27.0.dist-info/RECORD
trollimage-1.27.0.dist-info/WHEEL
trollimage-1.27.0.dist-info/top_level.txt
trollimage-1.27.0.dist-info/METADATA
trollimage-1.27.0.dist-info/licenses/LICENSE_RIO_COLOR.txt
trollimage-1.27.0.dist-info/licenses/LICENSE.txt
trollimage/colormap.py
trollimage/version.py
trollimage/colorspaces.py
trollimage/__init__.py
trollimage/xrimage.py
trollimage/_colorspaces.cpython-314-darwin.so
trollimage/py.typed
trollimage/utilities.py
trollimage/image.py
trollimage/_xrimage_rasterio.py
trollimage/tests/test_colormap.py
trollimage/tests/test_xrimage.py
trollimage/tests/test_image.py
trollimage/tests/__init__.py
trollimage/tests/utils.py
